llmexec/__init__.py
llmexec/exceptions.py
llmexec/executor.py
llmexec/utils.py
llmexec-0.1.1.dist-info/METADATA
llmexec-0.1.1.dist-info/WHEEL
llmexec-0.1.1.dist-info/top_level.txt
llmexec-0.1.1.dist-info/RECORD
