Metadata-Version: 2.1
Name: llmexec
Version: 0.1.1
Summary: Execute LLM-Generated Python Code Automatically
Home-page: https://github.com/Bam-Corp/llmexec
Author: Bam Corp
Author-email: spencer@bam.bot
Project-URL: Bug Tracker, https://github.com/Bam-Corp/llmexec/issues
Project-URL: Source Code, https://github.com/Bam-Corp/llmexec
Keywords: llmexec,code execution,ai-generated code
Classifier: Development Status :: 3 - Alpha
Classifier: Intended Audience :: Developers
Classifier: Topic :: Software Development :: Libraries
Classifier: License :: OSI Approved :: MIT License
Classifier: Programming Language :: Python :: 3
Classifier: Programming Language :: Python :: 3.7
Classifier: Programming Language :: Python :: 3.8
Classifier: Programming Language :: Python :: 3.9
Classifier: Programming Language :: Python :: 3.10
Classifier: Programming Language :: Python :: 3.11
Classifier: Programming Language :: Python :: 3.12
Requires-Python: >=3.7
Requires-Dist: RestrictedPython
Requires-Dist: rich
Requires-Dist: bleach
Requires-Dist: psutil
